.gitignore
LICENSE
MANIFEST.in
NAME
PKG-INFO
README.md
VERSION
env
requeriments.txt
setup.cfg
setup.py
websocketdatamanager/DjangoDataManager.py
websocketdatamanager/DjangoDataTestManager.py
websocketdatamanager/WebsocketDataManager.py
websocketdatamanager/__init__.py
websocketdatamanager/gendata_engine.py
websocketdatamanager/rmq2django.py
websocketdatamanager/rmq2ws.py
websocketdatamanager/rmq_engine.py
websocketdatamanager/test_rmq.py
websocketdatamanager/test_rmq2ws.py
websocketdatamanager/ws_client.py
websocketdatamanager/ws_client_channels.py
websocketdatamanager/ws_client_channels_users.py
websocketdatamanager/ws_server.py
websocketdatamanager/test/datagen_test.py
websocketdatamanager/test/django_test_manager.py
websocketdatamanager/test/rabbitmq_read.py