Metadata-Version: 2.1
Name: websocketdatamanager
Version: 0.1.10
Summary: Websocket data manager, from rmq to ws
Home-page: https://gitlab.com/pineiden/websocketsoftware
Author: David Pineda Osorio
Author-email: dpineda@csn.uchile.cl
License: GPLv3
Platform: UNKNOWN
